PyCorrCPI/__init__.py
PyCorrCPI/covariance.py
PyCorrCPI/data.py
PyCorrCPI/helpers_numba.py
PyCorrCPI/imports.py
PyCorrCPI/output_functions.py
PyCorrCPI-0.0.5.dist-info/LICENSE
PyCorrCPI-0.0.5.dist-info/METADATA
PyCorrCPI-0.0.5.dist-info/WHEEL
PyCorrCPI-0.0.5.dist-info/top_level.txt
PyCorrCPI-0.0.5.dist-info/RECORD
